{
  "id": "62c0736e-c89f-4a1f-baae-b4d4dc312cf0",
  "runner": "xgsd@v1",
  "name": "HTTP Request Example",
  "description": "An example workflow that makes an HTTP request",
  "package": "/xgsd-cli/examples/http",
  "start": "2025-09-01T23:08:34.432Z",
  "end": "2025-09-01T23:08:34.483Z",
  "duration": 470,
  "state": "completed",
  "config": {
    "name": "HTTP Request Example",
    "description": "An example workflow that makes an HTTP request",
    "runner": "xgsd@v1",
    "metadata": {},
    "mode": "chained",
    "enabled": true,
    "data": {
      "url": "https://jsonplaceholder.typicode.com/todos/1"
    },
    "options": {
      "timeout": 1000,
      "retries": 3
    },
    "collect": {
      "logs": true,
      "run": true
    },
    "steps": [
      {
        "name": "Fetch Data",
        "description": "no description",
        "action": "fetchData",
        "enabled": true,
        "data": {
          "url": "https://jsonplaceholder.typicode.com/todos/1"
        },
        "options": {
          "timeout": 1000,
          "retries": 3
        },
        "input": {
          "url": "https://jsonplaceholder.typicode.com/todos/1",
          "data": "some data"
        }
      },
      {
        "name": "Hash Result",
        "description": "no description",
        "action": "hashResult",
        "enabled": true,
        "data": {
          "url": "https://jsonplaceholder.typicode.com/todos/1"
        },
        "options": {
          "timeout": 1000,
          "retries": 3
        },
        "input": {
          "userId": 1,
          "id": 1,
          "title": "delectus aut autem",
          "completed": false
        }
      }
    ],
    "version": "1.0.0",
    "package": "/xgsd-cli/examples/http",
    "output": "/xgsd-cli/examples/http/runs/http-request-example",
    "node": {
      "os": "linux",
      "arch": "x64",
      "version": "v24.4.1",
      "processes": {
        "user": 237867,
        "system": 43524
      },
      "memory": {
        "rss": 82407424,
        "heapTotal": 30744576,
        "heapUsed": 13611712,
        "external": 2265470,
        "arrayBuffers": 47740
      }
    }
  },
  "steps": [
    {
      "name": "Fetch Data",
      "description": "no description",
      "state": "completed",
      "input": {
        "url": "https://jsonplaceholder.typicode.com/todos/1",
        "data": "some data"
      },
      "output": {
        "userId": 1,
        "id": 1,
        "title": "delectus aut autem",
        "completed": false
      },
      "max": 3,
      "attempt": 0,
      "error": null,
      "errors": [],
      "duration": 419,
      "startedAt": "2025-09-01T23:08:33.965Z",
      "endedAt": "2025-09-01T23:08:34.384Z"
    },
    {
      "name": "Hash Result",
      "description": "no description",
      "state": "completed",
      "input": {
        "userId": 1,
        "id": 1,
        "title": "delectus aut autem",
        "completed": false,
        "url": "https://jsonplaceholder.typicode.com/todos/1"
      },
      "output": "87399bb757c95c41e6880b8a42d05581b807f36da586e59df268db9f9584bd80",
      "max": 3,
      "attempt": 0,
      "error": null,
      "errors": [],
      "duration": 51,
      "startedAt": "2025-09-01T23:08:34.432Z",
      "endedAt": "2025-09-01T23:08:34.483Z"
    }
  ]
}
